guc_mail_scrapper.py
guc_mail_scrapper-0.1.1.dist-info/METADATA
guc_mail_scrapper-0.1.1.dist-info/WHEEL
guc_mail_scrapper-0.1.1.dist-info/RECORD
