Metadata-Version: 2.1
Name: guc-mail-scrapper
Version: 0.1.1
Summary: 
Author: Mathew Hany
Author-email: mathew.hanybb@gmail.com
Requires-Python: >=3.11,<4.0
Classifier: Programming Language :: Python :: 3
Classifier: Programming Language :: Python :: 3.11
Classifier: Programming Language :: Python :: 3.12
Requires-Dist: beautifulsoup4 (>=4.12.3,<5.0.0)
Requires-Dist: requests (>=2.32.3,<3.0.0)
